jheaps/__init__.py
jheaps/__version__.py
jheaps/_backend.cpython-36m-darwin.so
jheaps/backend.py
jheaps/libjheaps_capi.dylib
jheaps/types.py
jheaps/_internals/__init__.py
jheaps/_internals/_addressable_any_heaps.py
jheaps/_internals/_addressable_heaps.py
jheaps/_internals/_factories.py
jheaps/_internals/_heaps.py
jheaps/_internals/_utils.py
jheaps/_internals/_wrappers.py
jheaps-0.14.0.dist-info/LICENSE
jheaps-0.14.0.dist-info/METADATA
jheaps-0.14.0.dist-info/WHEEL
jheaps-0.14.0.dist-info/top_level.txt
jheaps-0.14.0.dist-info/RECORD
